freezeburn/__init__.py
freezeburn/cli.py
freezeburn/core.py
freezeburn-0.6.0.dist-info/licenses/LICENSE
tests/__init__.py
tests/conftest.py
tests/test_integration.py
freezeburn-0.6.0.dist-info/METADATA
freezeburn-0.6.0.dist-info/WHEEL
freezeburn-0.6.0.dist-info/entry_points.txt
freezeburn-0.6.0.dist-info/top_level.txt
freezeburn-0.6.0.dist-info/RECORD
