Metadata-Version: 2.4
Name: freezeburn
Version: 0.6.0
Summary: Freeze what you actually use. Generate requirements.txt from real imports and installed packages.
Author-email: dodogabrie <dodogabrie@users.noreply.github.com>
License: GPL-3.0
Project-URL: Homepage, https://github.com/dodogabrie/freezeburn
Project-URL: Repository, https://github.com/dodogabrie/freezeburn.git
Project-URL: Issues, https://github.com/dodogabrie/freezeburn/issues
Keywords: requirements,dependencies,imports,freeze,packaging
Classifier: Development Status :: 4 - Beta
Classifier: Environment :: Console
Classifier: Intended Audience :: Developers
Classifier: License :: OSI Approved :: GNU General Public License v3 (GPLv3)
Classifier: Operating System :: OS Independent
Classifier: Programming Language :: Python :: 3
Classifier: Programming Language :: Python :: 3.10
Classifier: Programming Language :: Python :: 3.11
Classifier: Programming Language :: Python :: 3.12
Classifier: Programming Language :: Python :: 3.13
Classifier: Topic :: Software Development :: Build Tools
Classifier: Topic :: System :: Software Distribution
Requires-Python: >=3.10
License-File: LICENSE
Provides-Extra: dev
Requires-Dist: pytest>=7.0; extra == "dev"
Dynamic: license-file
